uw_django_oidc-1.0.2.1.dist-info/licenses/LICENSE
uw_oidc/VERSION
uw_oidc/__init__.py
uw_oidc/exceptions.py
uw_oidc/id_token.py
uw_oidc/jwks.py
uw_oidc/logger.py
uw_oidc/middleware.py
uw_oidc/resources/uwidp/file/idp/profile/oidc/keyset
uw_oidc/tests/__init__.py
uw_oidc/tests/test_id_token.py
uw_oidc/tests/test_jwks.py
uw_oidc/tests/test_middleware.py
uw_django_oidc-1.0.2.1.dist-info/METADATA
uw_django_oidc-1.0.2.1.dist-info/WHEEL
uw_django_oidc-1.0.2.1.dist-info/top_level.txt
uw_django_oidc-1.0.2.1.dist-info/RECORD
