Metadata-Version: 2.4
Name: Uw-Django-Oidc
Version: 1.0.2.1
Summary: Midlleware handles Django request with UW OIDC id-token.
Home-page: https://github.com/uw-it-aca/uw-django-oidc
Author: UW-IT SETS
Author-email: aca-it@uw.edu
License: Apache License, Version 2.0
Classifier: Intended Audience :: Developers
Classifier: License :: OSI Approved :: Apache Software License
Classifier: Operating System :: OS Independent
Classifier: Programming Language :: Python
License-File: LICENSE
Requires-Dist: Django
Requires-Dist: UW-RestClients-Core
Requires-Dist: pyjwt
Requires-Dist: jwcrypto
Dynamic: author
Dynamic: author-email
Dynamic: classifier
Dynamic: description
Dynamic: home-page
Dynamic: license
Dynamic: license-file
Dynamic: requires-dist
Dynamic: summary
